mcp_dbutils/__init__.py
mcp_dbutils/audit.py
mcp_dbutils/base.py
mcp_dbutils/config.py
mcp_dbutils/log.py
mcp_dbutils/stats.py
mcp_dbutils/mysql/__init__.py
mcp_dbutils/mysql/config.py
mcp_dbutils/mysql/handler.py
mcp_dbutils/mysql/server.py
mcp_dbutils/postgres/__init__.py
mcp_dbutils/postgres/config.py
mcp_dbutils/postgres/handler.py
mcp_dbutils/postgres/server.py
mcp_dbutils/sqlite/__init__.py
mcp_dbutils/sqlite/config.py
mcp_dbutils/sqlite/handler.py
mcp_dbutils/sqlite/server.py
mseep_mcp_dbutils-1.0.8.dist-info/licenses/LICENSE
mseep_mcp_dbutils-1.0.8.dist-info/METADATA
mseep_mcp_dbutils-1.0.8.dist-info/WHEEL
mseep_mcp_dbutils-1.0.8.dist-info/entry_points.txt
mseep_mcp_dbutils-1.0.8.dist-info/top_level.txt
mseep_mcp_dbutils-1.0.8.dist-info/RECORD
